{
  "IconSourceDroid": "https://www.internetwideworld.com/Images/Droid/drawable-xxxhdpi/{0}.png",
  "IconSourceIos": "https://www.internetwideworld.com/Images/iOS/{0}@3x.png",
  "Markets": [
    {
      "SymbolString": "BTC",
      "DecimalPlaces": 2,
      "Rank": 1,
      "DisplayName": "Bitcoin (BTC)"
    },
    {
      "SymbolString": "ETH",
      "DecimalPlaces": 2,
      "Rank": 2,
      "DisplayName": "Etherium (ETH)"
    },
    {
      "SymbolString": "SOL",
      "DecimalPlaces": 2,
      "Rank": 6,
      "DisplayName": "Solana (SOL)"
    },
    {
      "SymbolString": "BNB",
      "DecimalPlaces": 2,
      "Rank": 5,
      "DisplayName": "Binance Coin (BNB)"
    },
    {
      "SymbolString": "XRP",
      "DecimalPlaces": 4,
      "Rank": 4,
      "DisplayName": "Ripple (XRP)"
    },
    {
      "SymbolString": "DOGE",
      "DecimalPlaces": 5,
      "Rank": 8,
      "DisplayName": "Dogecoin (DOGE)"
    },
    {
      "SymbolString": "ADA",
      "DecimalPlaces": 4,
      "Rank": 10,
      "DisplayName": "Cardano (ADA)"
    },
    {
      "SymbolString": "TRX",
      "DecimalPlaces": 4,
      "Rank": 9,
      "DisplayName": "Tron (TRX)"
    },
    {
      "SymbolString": "AVAX",
      "DecimalPlaces": 2,
      "Rank": 15,
      "DisplayName": "Avalanche (AVAX)"
    },
    {
      "SymbolString": "SHIB",
      "DecimalPlaces": 8,
      "Rank": 17,
      "DisplayName": "Shiba Inu (SHIB)"
    },
    {
      "SymbolString": "XLM",
      "DecimalPlaces": 4,
      "Rank": 16,
      "DisplayName": "Stellar (XLM)"
    },
    {
      "SymbolString": "DOT",
      "DecimalPlaces": 3,
      "Rank": 26,
      "DisplayName": "Polkadot (DOT)"
    },
    {
      "SymbolString": "LINK",
      "DecimalPlaces": 2,
      "Rank": 14,
      "DisplayName": "Chainlink (LINK)"
    },
    {
      "SymbolString": "BCH",
      "DecimalPlaces": 1,
      "Rank": 23,
      "DisplayName": "Bitcoin Cash (BCH)"
    },
    {
      "SymbolString": "SUI",
      "DecimalPlaces": 4,
      "Rank": 18,
      "DisplayName": "Sui (SUI)"
    },
    {
      "SymbolString": "NEAR",
      "DecimalPlaces": 3,
      "Rank": 44,
      "DisplayName": "NEAR (NEAR)"
    },
    {
      "SymbolString": "UNI",
      "DecimalPlaces": 3,
      "Rank": 36,
      "DisplayName": "Uniswap (UNI)"
    },
    {
      "SymbolString": "LTC",
      "DecimalPlaces": 2,
      "Rank": 25,
      "DisplayName": "Litecoin (LTC)"
    },
    {
      "SymbolString": "APT",
      "DecimalPlaces": 2,
      "Rank": 41,
      "DisplayName": "Aptos (APT)"
    },
    {
      "SymbolString": "ICP",
      "DecimalPlaces": 3,
      "Rank": 47,
      "DisplayName": "Internet Computer (ICP)"
    },
    {
      "SymbolString": "HBAR",
      "DecimalPlaces": 5,
      "Rank": 21,
      "DisplayName": "Hadera Hashgraph (HBAR)"
    },
    {
      "SymbolString": "ETC",
      "DecimalPlaces": 2,
      "Rank": 51,
      "DisplayName": "Etherium Classic (ETC)"
    },
    {
      "SymbolString": "FET",
      "DecimalPlaces": 3,
      "Rank": 73,
      "DisplayName": "Fetch.ai (FET)"
    },
    {
      "SymbolString": "ARB",
      "DecimalPlaces": 4,
      "Rank": 69,
      "DisplayName": "Arbitrum (ARB)"
    },
    {
      "SymbolString": "FIL",
      "DecimalPlaces": 3,
      "Rank": 64,
      "DisplayName": "FileCoin (FIL)"
    },
    {
      "SymbolString": "STX",
      "DecimalPlaces": 3,
      "Rank": 87,
      "DisplayName": "Stacks (STX)"
    },
    {
      "SymbolString": "VET",
      "DecimalPlaces": 5,
      "Rank": 57,
      "DisplayName": "VeChain (VET)"
    },
    {
      "SymbolString": "ATOM",
      "DecimalPlaces": 3,
      "Rank": 58,
      "DisplayName": "Cosmos (ATOM)"
    },
    {
      "SymbolString": "AAVE",
      "DecimalPlaces": 2,
      "Rank": 54,
      "DisplayName": "AAVE (AAVE)"
    },
    {
      "SymbolString": "OP",
      "DecimalPlaces": 3,
      "Rank": 76,
      "DisplayName": "Optimism (OP)"
    },
    {
      "SymbolString": "IMX",
      "DecimalPlaces": 3,
      "Rank": 102,
      "DisplayName": "Immutable X (IMX)"
    },
    {
      "SymbolString": "INJ",
      "DecimalPlaces": 2,
      "Rank": 96,
      "DisplayName": "Injective (INJ)"
    },
    {
      "SymbolString": "ALGO",
      "DecimalPlaces": 4,
      "Rank": 67,
      "DisplayName": "Algorand (ALGO)"
    },
    {
      "SymbolString": "GRT",
      "DecimalPlaces": 4,
      "Rank": 101,
      "DisplayName": "The Graph (GRT)"
    },
    {
      "SymbolString": "THETA",
      "DecimalPlaces": 3,
      "Rank": 106,
      "DisplayName": "Theta Network (THETA)"
    },
    {
      "SymbolString": "RUNE",
      "DecimalPlaces": 3,
      "Rank": 158,
      "DisplayName": "THORChain (RUNE)"
    },
    {
      "SymbolString": "MKR",
      "DecimalPlaces": 0,
      "Rank": 75,
      "DisplayName": "Maker (MKR)"
    },
    {
      "SymbolString": "GALA",
      "DecimalPlaces": 5,
      "Rank": 112,
      "DisplayName": "GALA (GALA)"
    },
    {
      "SymbolString": "SAND",
      "DecimalPlaces": 4,
      "Rank": 113,
      "DisplayName": "The Sandbox (SAND)"
    },
    {
      "SymbolString": "IOTA",
      "DecimalPlaces": 4,
      "Rank": 85,
      "DisplayName": "MIOTA (IOTA)"
    },
    {
      "SymbolString": "AR",
      "DecimalPlaces": 2,
      "Rank": 173,
      "DisplayName": "Arweave (AR)"
    },
    {
      "SymbolString": "FLOW",
      "DecimalPlaces": 3,
      "Rank": 126,
      "DisplayName": "FLOW (FLOW)"
    },
    {
      "SymbolString": "QNT",
      "DecimalPlaces": 1,
      "Rank": 85,
      "DisplayName": "Quant (QNT)"
    },
    {
      "SymbolString": "XTZ",
      "DecimalPlaces": 3,
      "Rank": 125,
      "DisplayName": "Tezos (XTZ)"
    },
    {
      "SymbolString": "EOS",
      "DecimalPlaces": 4,
      "Rank": 89,
      "DisplayName": "EOS (EOS)"
    },
    {
      "SymbolString": "ENS",
      "DecimalPlaces": 2,
      "Rank": 138,
      "DisplayName": "Etherium Name Service (ENS)"
    },
    {
      "SymbolString": "AXS",
      "DecimalPlaces": 3,
      "Rank": 172,
      "DisplayName": "Axie Infinity (AXS)"
    },
    {
      "SymbolString": "MANA",
      "DecimalPlaces": 4,
      "Rank": 140,
      "DisplayName": "Decentraland (MANA)"
    },
    {
      "SymbolString": "EGLD",
      "DecimalPlaces": 2,
      "Rank": 159,
      "DisplayName": "Elrond (EGLD)"
    },
    {
      "SymbolString": "NEO",
      "DecimalPlaces": 2,
      "Rank": 165,
      "DisplayName": "NEO (NEO)"
    },
    {
      "SymbolString": "XEC",
      "DecimalPlaces": 8,
      "Rank": 161,
      "DisplayName": "eCash (XEC)"
    },
    {
      "SymbolString": "APE",
      "DecimalPlaces": 3,
      "Rank": 183,
      "DisplayName": "ApeCoin (APE)"
    },
    {
      "SymbolString": "NEXO",
      "DecimalPlaces": 3,
      "Rank": 78,
      "DisplayName": "NEXO (NEXO)"
    },
    {
      "SymbolString": "MINA",
      "DecimalPlaces": 4,
      "Rank": 214,
      "DisplayName": "Mina Protocol (MINA)"
    },
    {
      "SymbolString": "CAKE",
      "DecimalPlaces": 3,
      "Rank": 120,
      "DisplayName": "PancakeSwap (CAKE)"
    },
    {
      "SymbolString": "ZEC",
      "DecimalPlaces": 2,
      "Rank": 122,
      "DisplayName": "ZCash (ZEC)"
    },
    {
      "SymbolString": "CHZ",
      "DecimalPlaces": 4,
      "Rank": 169,
      "DisplayName": "Chiliz (CHZ)"
    },
    {
      "SymbolString": "SNX",
      "DecimalPlaces": 3,
      "Rank": 240,
      "DisplayName": "Synthetix Network Token (SNX)"
    },
    {
      "SymbolString": "AMP",
      "DecimalPlaces": 6,
      "Rank": 199,
      "DisplayName": "AMP (AMP)"
    },
    {
      "SymbolString": "GNO",
      "DecimalPlaces": 1,
      "Rank": 211,
      "DisplayName": "Gnosis (GNO)"
    },
    {
      "SymbolString": "CKB",
      "DecimalPlaces": 6,
      "Rank": 261,
      "DisplayName": "Nervos Network (CKB)"
    },
    {
      "SymbolString": "ROSE",
      "DecimalPlaces": 5,
      "Rank": 295,
      "DisplayName": "Oasis Network (ROSE)"
    },
    {
      "SymbolString": "COMP",
      "DecimalPlaces": 2,
      "Rank": 176,
      "DisplayName": "Compound (COMP)"
    },
    {
      "SymbolString": "CRV",
      "DecimalPlaces": 4,
      "Rank": 99,
      "DisplayName": "Curve DAO Token (CRV)"
    },
    {
      "SymbolString": "ASTR",
      "DecimalPlaces": 4,
      "Rank": 255,
      "DisplayName": "Astar (ASTR)"
    },
    {
      "SymbolString": "KAVA",
      "DecimalPlaces": 4,
      "Rank": 143,
      "DisplayName": "KAVA (KAVA)"
    },
    {
      "SymbolString": "KSM",
      "DecimalPlaces": 2,
      "Rank": 241,
      "DisplayName": "Kasuma (KSM)"
    },
    {
      "SymbolString": "1INCH",
      "DecimalPlaces": 4,
      "Rank": 231,
      "DisplayName": "1INCH (1INCH)"
    },
    {
      "SymbolString": "LPT",
      "DecimalPlaces": 3,
      "Rank": 300,
      "DisplayName": "Livepeer (LPT)"
    },
    {
      "SymbolString": "PAXG",
      "DecimalPlaces": 0,
      "Rank": 103,
      "DisplayName": "PAX Gold (PAXG)"
    },
    {
      "SymbolString": "TFUEL",
      "DecimalPlaces": 5,
      "Rank": 232,
      "DisplayName": "Theta Fuel (TFUEL)"
    },
    {
      "SymbolString": "ENJ",
      "DecimalPlaces": 4,
      "Rank": 298,
      "DisplayName": "Enjin Coin (ENJ)"
    },
    {
      "SymbolString": "HOT",
      "DecimalPlaces": 6,
      "Rank": 286,
      "DisplayName": "Holo (HOT)"
    },
    {
      "SymbolString": "WOO",
      "DecimalPlaces": 4,
      "Rank": 299,
      "DisplayName": "WOO (WOO)"
    },
    {
      "SymbolString": "ZIL",
      "DecimalPlaces": 5,
      "Rank": 243,
      "DisplayName": "Zilliqa (ZIL)"
    },
    {
      "SymbolString": "ZRX",
      "DecimalPlaces": 4,
      "Rank": 249,
      "DisplayName": "0x (ZRX)"
    },
    {
      "SymbolString": "CELO",
      "DecimalPlaces": 4,
      "Rank": 292,
      "DisplayName": "CELO (CELO)"
    },
    {
      "SymbolString": "BAT",
      "DecimalPlaces": 4,
      "Rank": 264,
      "DisplayName": "Basic Attention Token (BAT)"
    },
    {
      "SymbolString": "DASH",
      "DecimalPlaces": 2,
      "Rank": 220,
      "DisplayName": "DASH (DASH)"
    },
    {
      "SymbolString": "IOTX",
      "DecimalPlaces": 5,
      "Rank": 273,
      "DisplayName": "IoTeX (IOTX)"
    },
    {
      "SymbolString": "ANKR",
      "DecimalPlaces": 5,
      "Rank": 288,
      "DisplayName": "ANKR (ANKR)"
    },
    {
      "SymbolString": "ELF",
      "DecimalPlaces": 4,
      "Rank": 297,
      "DisplayName": "aelf (ELF)"
    },
    {
      "SymbolString": "SC",
      "DecimalPlaces": 6,
      "Rank": 291,
      "DisplayName": "Siacoin (SC)"
    },
    {
      "SymbolString": "C98",
      "DecimalPlaces": 4,
      "Rank": 235,
      "DisplayName": "Coin98 (C98)"
    },
    {
      "SymbolString": "OSMO",
      "DecimalPlaces": 4,
      "Rank": 296,
      "DisplayName": "Osmosis (OSMO)"
    },
    {
      "SymbolString": "QTUM",
      "DecimalPlaces": 3,
      "Rank": 250,
      "DisplayName": "QTUM (QTUM)"
    },
    {
      "SymbolString": "JST",
      "DecimalPlaces": 5,
      "Rank": 200,
      "DisplayName": "JUST (JST)"
    },
    {
      "SymbolString": "SKL",
      "DecimalPlaces": 5,
      "Rank": 302,
      "DisplayName": "SKALE (SKL)"
    },
    {
      "SymbolString": "GAS",
      "DecimalPlaces": 3,
      "Rank": 262,
      "DisplayName": "Gas (GAS)"
    },
    {
      "SymbolString": "KDA",
      "DecimalPlaces": 4,
      "Rank": 299,
      "DisplayName": "Kadena (KDA)"
    },
    {
      "SymbolString": "MASK",
      "DecimalPlaces": 3,
      "Rank": 250,
      "DisplayName": "Mask Network (MASK)"
    },
    {
      "SymbolString": "RVN",
      "DecimalPlaces": 5,
      "Rank": 299,
      "DisplayName": "Ravencoin (RVN)"
    },
    {
      "SymbolString": "TRB",
      "DecimalPlaces": 2,
      "Rank": 266,
      "DisplayName": "Tellor Tributes (TRB)"
    },
    {
      "SymbolString": "SYS",
      "DecimalPlaces": 4,
      "Rank": 285,
      "DisplayName": "Syscoin (SYS)"
    },
    {
      "SymbolString": "IOST",
      "DecimalPlaces": 6,
      "Rank": 290,
      "DisplayName": "IOST (ISOT)"
    },
    {
      "SymbolString": "CVX",
      "DecimalPlaces": 3,
      "Rank": 283,
      "DisplayName": "Convex Finance (CVX)"
    },
    {
      "SymbolString": "ONE",
      "DecimalPlaces": 5,
      "Rank": 300,
      "DisplayName": "Harmony (ONE)"
    },
    {
      "SymbolString": "API3",
      "DecimalPlaces": 3,
      "Rank": 293,
      "DisplayName": "API3 (API3)"
    },
    {
      "SymbolString": "DGB",
      "DecimalPlaces": 5,
      "Rank": 281,
      "DisplayName": "DigiByte (DBG)"
    },
    {
      "SymbolString": "DENT",
      "DecimalPlaces": 6,
      "Rank": 293,
      "DisplayName": "DENT (DENT)"
    },
    {
      "SymbolString": "LRC",
      "DecimalPlaces": 4,
      "Rank": 298,
      "DisplayName": "Loopring (LRC)"
    },
    {
      "SymbolString": "KNC",
      "DecimalPlaces": 4,
      "Rank": 295,
      "DisplayName": "Kyber Network Crystal (KNC)"
    },
    {
      "SymbolString": "SCRT",
      "DecimalPlaces": 4,
      "Rank": 296,
      "DisplayName": "Secret (SCRT)"
    },
    {
      "SymbolString": "DCR",
      "DecimalPlaces": 2,
      "Rank": 239,
      "DisplayName": "Decred (DCR)"
    },
    {
      "SymbolString": "BSW",
      "DecimalPlaces": 4,
      "Rank": 297,
      "DisplayName": "Biswap (BSW)"
    },
    {
      "SymbolString": "ONT",
      "DecimalPlaces": 4,
      "Rank": 293,
      "DisplayName": "Ontology (ONT)"
    },
    {
      "SymbolString": "SXP",
      "DecimalPlaces": 4,
      "Rank": 298,
      "DisplayName": "SXP (SXP)"
    },
    {
      "SymbolString": "WAXP",
      "DecimalPlaces": 5,
      "Rank": 298,
      "DisplayName": "WAX (WAXP)"
    },
    {
      "SymbolString": "ZEN",
      "DecimalPlaces": 2,
      "Rank": 294,
      "DisplayName": "Horizen (ZEN)"
    },
    {
      "SymbolString": "XNO",
      "DecimalPlaces": 3,
      "Rank": 296,
      "DisplayName": "Nano (XNO)"
    },
    {
      "SymbolString": "HIVE",
      "DecimalPlaces": 4,
      "Rank": 298,
      "DisplayName": "HIVE (HIVE)"
    },
    {
      "SymbolString": "SLP",
      "DecimalPlaces": 6,
      "Rank": 298,
      "DisplayName": "Smooth Love Potion (SLP)"
    },
    {
      "SymbolString": "YFI",
      "DecimalPlaces": 0,
      "Rank": 298,
      "DisplayName": "yearn.finance (YFI)"
    },
    {
      "SymbolString": "GLMR",
      "DecimalPlaces": 4,
      "Rank": 296,
      "DisplayName": "Moonbeam (GLMR)"
    },
    {
      "SymbolString": "ICX",
      "DecimalPlaces": 4,
      "Rank": 299,
      "DisplayName": "ICON (ICX)"
    },
    {
      "SymbolString": "LSK",
      "DecimalPlaces": 3,
      "Rank": 299,
      "DisplayName": "Lisk (LSK)"
    },
    {
      "SymbolString": "POWR",
      "DecimalPlaces": 4,
      "Rank": 299,
      "DisplayName": "Power Ledger (POWR)"
    },
    {
      "SymbolString": "SUSHI",
      "DecimalPlaces": 3,
      "Rank": 292,
      "DisplayName": "SUSHI (SUSHI)"
    },
    {
      "SymbolString": "MAGIC",
      "DecimalPlaces": 4,
      "Rank": 300,
      "DisplayName": "Magic (MAGIC)"
    },
    {
      "SymbolString": "FXS",
      "DecimalPlaces": 3,
      "Rank": 300,
      "DisplayName": "Frax Share (FXS)"
    },
    {
      "SymbolString": "AUDIO",
      "DecimalPlaces": 4,
      "Rank": 300,
      "DisplayName": "Audius (AUDIO)"
    },
    {
      "SymbolString": "UMA",
      "DecimalPlaces": 3,
      "Rank": 297,
      "DisplayName": "UMA (UMA)"
    },
    {
      "SymbolString": "FLUX",
      "DecimalPlaces": 4,
      "Rank": 294,
      "DisplayName": "FLUX (FLUX)"
    }
  ]
}
